{
    "AS_Image_e310ed4cad51499da8f210a794972e70": {
        "id": "AS_Image_e310ed4cad51499da8f210a794972e70",
        "type": "ACTION_SEQUENCE",
        "params": [{
            "datatype": "collection",
            "name": "eventobject"
        }, {
            "datatype": "string",
            "name": "x"
        }, {
            "datatype": "string",
            "name": "y"
        }],
        "contextObj": {
            "name": "frmEComplaintCategories",
            "type": "forms",
            "platform": "",
            "KUID": "aa3a8d906c9946c2b289f049ed23b43d"
        },
        "language": "js",
        "actions": [{
            "id": "NAVIGATE_TO_FORM__b62c2c846fce4515964049a8a575abc4",
            "type": "NAVIGATE_TO_FORM",
            "formId": "frmEComplaintsDashboard",
            "formKUID": "i8f5021dc1ca49a499f141fa7086e1db",
            "projectName": "RefEComplaintsMA",
            "mappings": {},
            "mappingsOrder": [],
            "parentId": null,
            "enableMappingEditor": true,
            "package": "",
            "isCustomInput": false
        }]
    }
}