{
    "DNDConfig": null,
    "_height_": {
        "type": "string",
        "value": "20dp"
    },
    "_left_": {
        "type": "string",
        "value": "0dp"
    },
    "_margin_": [
        0,
        0,
        0,
        0
    ],
    "_orientation_": 6,
    "_padding_": [
        0,
        0,
        0,
        0
    ],
    "_percent_": true,
    "_skin_": "s1df16dcc35045068a70a4aee877385a",
    "_top_": {
        "type": "number",
        "value": "0"
    },
    "_width_": {
        "type": "string",
        "value": "100%"
    },
    "allboxes": [],
    "autogrowmode": 0,
    "canUpdateUI": true,
    "children": [
        "lblCreateDateTime",
        "lblCreateDateTimeValue"
    ],
    "clipbounds": false,
    "containerId": true,
    "containerweight": 100,
    "enablescrolling": true,
    "id": "flxCreatedDateTime",
    "info": null,
    "iscustomlayout": false,
    "isvisible": true,
    "kuid": "d1d5cb4611c44540ad1b056324f737b4",
    "layouttype": 3,
    "name": "kony.ui.FlexContainer",
    "parent": "flxSegRowRecord",
    "pf": "tplSegRowRecord",
    "retaincontentalignment": false,
    "retainflexpositionproperties": false,
    "retainflowhorizontalalignment": false,
    "snapgridsize": 10,
    "snaptogrid": true,
    "wType": "FlexContainer",
    "widgetalignment": 1,
    "zindex": 1
}