<?xml version="1.0" encoding="UTF-8" standalone="yes"?>
<service serviceGroup="" cachable="false" cacheduration="" customOperation="false" description="" endpoint="" groupType="" id="getWeatherDetails" passwordencrypted="" security="authorized_app_user" type="CompositeConnector" smscode="" smsenabled="false">
    <service-config>
        <config-param api-version="" appid="" name="preprocessorname" value=""/>
        <config-param api-version="" appid="" name="postprocessorJS" value=""/>
        <config-param api-version="" appid="" name="preprocessorJS" value=""/>
        <config-param api-version="" appid="" name="postprocessorname" value=""/>
        <config-param api-version="" appid="" name="exec_type" value="Sequential"/>
        <config-param api-version="" appid="" name="kony_http_supported_methods" value="POST"/>
        <config-param api-version="1.0" appid="RefVMXBootcampLocationLookup" name="service" value="getLocationDetails"/>
        <config-param api-version="1.0" appid="RefVMXBootcampWeatherFeed" name="service" value="getWeatherDetails"/>
    </service-config>
    <service-input passthrough="false" isExtended="false"/>
    <service-output passthrough="false" isExtended="false"/>
</service>
